{
	"label": "Art Movements",
	"children": [
		{"label": "Renaissance",
		"children": [
			{"label": "Italian Renaissance",
			"start": 1275,
			"end": 1602},
			{"label": "Renaissance Classicism",
			"start": 1475,
			"end": 1602},
			{"label": "Early Netherlandish Painting",
			"start": 1400,
			"end": 1500}
		]
		},
		{"label": "Renaissance to Neoclassicism",
		"children": [
			{"label": "Mannerism and Late Renaissance",
			"start": 1520,
			"end": 1600},
			{"label": "Boroque",
			"start": 1600,
			"end": 1730},
			{"label": "Dutch Golden Age Painting",
			"start": 1702,
			"end": 1730},
			{"label": "Flemish Boroque Painting",
			"start": 1585,
			"end": 1700},
			{"label": "Rococo",
			"start": 1720,
			"end": 1780},
			{"label": "Neoclassicism",
			"start": 1750,
			"end": 1830}
		]
		},
		{"label": "Romanticism",
		"children": [
			{"label": "Nazarene Movement",
			"start": 1820,
			"end": 1847},
			{"label": "The Ancients",
			"start": 1825,
			"end": 1845},
			{"label": "Purismo",
			"start": 1825,
			"end": 1845},
			{"label": "Düsseldorf school",
			"start": 1825,
			"end": 1865},
			{"label": "Hudson River school",
			"start": 1855,
			"end": 1880},
			{"label": "Luminism",
			"start": 1855,
			"end": 1875}
	]
},
		{"label": "Romanticism to Modern Art",
		"children": [
			{"label": "Norwich school",
			"start": 1803,
			"end": 1833},
			{"label": "Biedermeier",
			"start": 1815,
			"end": 1848},
			{"label": "Photography",
			"start": 1830,
			"end": 2015},
			{"label": "Realism",
			"start": 1830,
			"end": 1870},
			{"label": "Barbizon school ",
			"start": 1830,
			"end": 1870},
			{"label": "Peredvizhniki",
			"start": 1870,
			"end": 1923},
			{"label": "Hague School",
			"start": 1870,
			"end": 1900},
			{"label": "American Barbizon school",
			"start": 1853,
			"end": 1895},
			{"label": "Spanish Eclecticism",
			"start": 1845,
			"end": 1890},
			{"label": "Macchiaioli",
			"start": 1850,
			"end": 1859},
			{"label": "Pre-Raphaelite Brotherhood",
			"start": 1848,
			"end": 1854}
	]
},
		{"label": "Modern Art",
		"children": [
			{"label": "Impressionism",
			"start": 1860,
			"end": 1890,
			"children": [
				{"label": "American Impressionism",
				"start": 1880,
				"end": 1890},
				{"label": "Cos Cob Art Colony",
				"start": 1890,
				"end": 1899},
				{"label": "Heidelberg School",
				"start": 1887,
				"end": 1890}
			]},
			{"label": "Arts and Crafts",
			"start": 1880,
			"end": 1910},
			{"label": "Tonalism",
			"start": 1880,
			"end": 1920},
			{"label": "Symbolism",
			"start": 1880,
			"end": 1910,
			"children": [
				{"label": "Russian Symbolism",
				"start": 1884,
				"end": 1910},
				{"label": "Aesthetic Movement",
				"start": 1868,
				"end": 1901}
			]},
			{"label": "Post-Impressionism",
			"start": 1886,
			"end": 1905,
			"children": [
				{"label": "Les Nabis",
				"start": 1888,
				"end": 1900},
				{"label": "Cloisonnism",
				"start": 1884,
				"end": 1886},
				{"label": "Synthetism",
				"start": 1887,
				"end": 1893}
			]},
			{"label": "Neo-Impressionism",
			"start": 1886,
			"end": 1906,
			"children": [
				{"label": "Pointillism",
				"start": 1879,
				"end": 1906},
				{"label": "Divisionism",
				"start": 1880,
				"end": 1880}
			]},
			{"label": "Art Nouveau",
			"start": 1890,
			"end": 1914,
			"children": [
				{"label": "Vienna Secession",
				"start": 1897,
				"end": 1914},
				{"label": "Jugendstil",
				"start": 1890,
				"end": 1914},
				{"label": "Modernisme",
				"start": 1890,
				"end": 1910}
			]},
			{"label": "Russian avant-garde",
			"start": 1890,
			"end": 1930},
			{"label": "Art à la Rue",
			"start": 1890,
			"end": 1905},
			{"label": "Young Poland",
			"start": 1890,
			"end": 1918},
			{"label": "Mir iskusstva",
			"start": 1889,
			"end": 1900},
			{"label": "Hagenbund",
			"start": 1900,
			"end": 1930},
			{"label": "Fauvism",
			"start": 1904,
			"end": 1909},
			{"label": "Expressionism",
			"start": 1905,
			"end": 1930},
			{"label": "Die Brücke",
			"start": 1905,
			"end": 1913},
			{"label": "Der Blaue Reiter",
			"start": 1911,
			"end": 1912},
			{"label": "Bloomsbury Group",
			"start": 1905,
			"end": 1945}
			]
		},
		{"label": "Contemporary Art",
		"children": [
			{"label": "Vienna School of Fantastic Realism",
			"start": 1946,
			"end": 1947},
			{"label": "Neo-Dada",
			"start": 1950,
			"end": 1959},
			{"label": "International Typographic Style",
			"start": 1950,
			"end": 1959},
			{"label": "Soviet Nonconformist Art",
			"start": 1953,
			"end": 1986},
			{"label": "Painters Eleven",
			"start": 1954,
			"end": 1960},
			{"label": "Pop Art",
			"start": 1953,
			"end": 1957},
			{"label": "Woodlands School",
			"start": 1958,
			"end": 1962},
			{"label": "Situationism",
			"start": 1957,
			"end": 1973},
			{"label": "New realism",
			"start": 1960,
			"end": 2015},
			{"label": "Magic realism",
			"start": 1960,
			"end": 1969},
			{"label": "Minimalism",
			"start": 1960,
			"end": 2015},
			{"label": "Hard-edge painting",
			"start": 1960,
			"end": 1963},
			{"label": "Fluxus",
			"start": 1960,
			"end": 1977},
			{"label": "Happening",
			"start": 1960,
			"end": 2015}
		]}
		]

}